SiamBOMB/__init__.py
SiamBOMB/downloader.py
SiamBOMB/launcher.py
SiamBOMB/pyqt5/__init__.py
SiamBOMB/pyqt5/dracula.qss
SiamBOMB/pyqt5/model_list.json
SiamBOMB/pyqt5/rc_ui.py
SiamBOMB/pyqt5/window_base.py
SiamBOMB/pyqt5/window_configure.py
SiamBOMB/pyqt5/window_main.py
SiamBOMB/pyqt5/window_ui.py
SiamBOMB/pysot/__init__.py
SiamBOMB/pysot/core/__init__.py
SiamBOMB/pysot/core/config.py
SiamBOMB/pysot/core/xcorr.py
SiamBOMB/pysot/datasets/__init__.py
SiamBOMB/pysot/datasets/anchor_target.py
SiamBOMB/pysot/datasets/augmentation.py
SiamBOMB/pysot/datasets/dataset.py
SiamBOMB/pysot/experiments/__init__.py
SiamBOMB/pysot/experiments/siammaske_r50_l3/__init__.py
SiamBOMB/pysot/experiments/siammaske_r50_l3/config.yaml
SiamBOMB/pysot/models/__init__.py
SiamBOMB/pysot/models/init_weight.py
SiamBOMB/pysot/models/loss.py
SiamBOMB/pysot/models/model_builder.py
SiamBOMB/pysot/models/backbone/__init__.py
SiamBOMB/pysot/models/backbone/alexnet.py
SiamBOMB/pysot/models/backbone/mobile_v2.py
SiamBOMB/pysot/models/backbone/resnet_atrous.py
SiamBOMB/pysot/models/head/__init__.py
SiamBOMB/pysot/models/head/mask.py
SiamBOMB/pysot/models/head/rpn.py
SiamBOMB/pysot/models/neck/__init__.py
SiamBOMB/pysot/models/neck/neck.py
SiamBOMB/pysot/tracker/__init__.py
SiamBOMB/pysot/tracker/base_tracker.py
SiamBOMB/pysot/tracker/multiple_tracker.py
SiamBOMB/pysot/tracker/siammask_e_tracker.py
SiamBOMB/pysot/tracker/siammask_tracker.py
SiamBOMB/pysot/tracker/siamrpn_tracker.py
SiamBOMB/pysot/tracker/siamrpnlt_tracker.py
SiamBOMB/pysot/tracker/tracker_builder.py
SiamBOMB/pysot/utils/__init__.py
SiamBOMB/pysot/utils/anchor.py
SiamBOMB/pysot/utils/average_meter.py
SiamBOMB/pysot/utils/bbox.py
SiamBOMB/pysot/utils/distributed.py
SiamBOMB/pysot/utils/log_helper.py
SiamBOMB/pysot/utils/lr_scheduler.py
SiamBOMB/pysot/utils/misc.py
SiamBOMB/pysot/utils/model_load.py
SiamBOMB/pytracking/__init__.py
SiamBOMB/pytracking/admin/__init__.py
SiamBOMB/pytracking/admin/environment.py
SiamBOMB-0.0.4.dist-info/LICENSE
SiamBOMB-0.0.4.dist-info/METADATA
SiamBOMB-0.0.4.dist-info/WHEEL
SiamBOMB-0.0.4.dist-info/top_level.txt
SiamBOMB-0.0.4.dist-info/RECORD
