Metadata-Version: 2.1
Name: SiamBOMB
Version: 0.0.4
Summary: SiamBOMB: Siamese network using Background information for real-time Online Multi-species home-cage animal Behavioral analysis
Home-page: https://github.com/JackieZhai/SiamBOMB
Author: JackieZhai
Author-email: jackieturing@gmail.com
License: UNKNOWN
Project-URL: Bug Tracker, https://github.com/JackieZhai/SiamBOMB/issues
Project-URL: Request Tracker, https://github.com/JackieZhai/SiamBOMB/pulls
Platform: UNKNOWN
Classifier: Programming Language :: Python :: 3
Classifier: License :: OSI Approved :: MIT License
Classifier: Operating System :: OS Independent
Requires-Python: >=3.6
License-File: LICENSE
Requires-Dist: numpy
Requires-Dist: opencv-python
Requires-Dist: pyyaml
Requires-Dist: yacs
Requires-Dist: tqdm
Requires-Dist: colorama
Requires-Dist: matplotlib
Requires-Dist: cython
Requires-Dist: tensorboardX
Requires-Dist: imutils
Requires-Dist: pandas
Requires-Dist: scikit-image
Requires-Dist: visdom
Requires-Dist: tb-nightly
Requires-Dist: tikzplotlib
Requires-Dist: gdown
